depth_anything_v2/dinov2.py
depth_anything_v2/dinov2_layers/__init__.py
depth_anything_v2/dinov2_layers/attention.py
depth_anything_v2/dinov2_layers/block.py
depth_anything_v2/dinov2_layers/drop_path.py
depth_anything_v2/dinov2_layers/layer_scale.py
depth_anything_v2/dinov2_layers/mlp.py
depth_anything_v2/dinov2_layers/patch_embed.py
depth_anything_v2/dinov2_layers/swiglu_ffn.py
depth_anything_v2/dpt.py
depth_anything_v2/util/blocks.py
depth_anything_v2/util/transform.py
depth_anything_v2-0.1.0.dist-info/LICENSE
depth_anything_v2-0.1.0.dist-info/METADATA
depth_anything_v2-0.1.0.dist-info/WHEEL
depth_anything_v2-0.1.0.dist-info/RECORD
