Metadata-Version: 2.3
Name: depth-anything-v2
Version: 0.1.0
Summary: 
Author: tsmorz
Author-email: tonysmoragiewicz@gmail.com
Requires-Python: >=3.12
Classifier: Programming Language :: Python :: 3
Classifier: Programming Language :: Python :: 3.12
Classifier: Programming Language :: Python :: 3.13
Requires-Dist: gradio-imageslider (>=0.0.20,<0.0.21)
Requires-Dist: matplotlib (>=3.10.3,<4.0.0)
Requires-Dist: opencv-python (>=4.12.0.88,<5.0.0.0)
Requires-Dist: torch (>=2.7.1,<3.0.0)
Requires-Dist: torchvision (>=0.22.1,<0.23.0)
